restic/__init__.py
restic/_cli.py
restic/_click.py
restic/_constants.py
restic/_models.py
restic/_repo.py
restic/_utilities.py
restic/commands/__init__.py
restic/commands/_backup.py
restic/commands/_copy.py
restic/commands/_forget.py
restic/commands/_init.py
restic/commands/_restore.py
restic/commands/_snapshots.py
restic/commands/_unlock.py
restic/py.typed
dycw_restic-0.6.6.dist-info/WHEEL
dycw_restic-0.6.6.dist-info/entry_points.txt
dycw_restic-0.6.6.dist-info/METADATA
dycw_restic-0.6.6.dist-info/RECORD
