Metadata-Version: 2.3
Name: dycw-restic
Version: 0.6.6
Summary: Library to operate `restic`
Author: Derek Wan
Author-email: Derek Wan <d.wan@icloud.com>
Requires-Dist: click>=8.3.1
Requires-Dist: dycw-utilities>=0.188.12
Requires-Dist: pydantic>=2.12.5
Requires-Dist: click==8.3.1 ; extra == 'cli'
Requires-Dist: dycw-utilities==0.188.12 ; extra == 'cli'
Requires-Dist: pydantic==2.12.5 ; extra == 'cli'
Requires-Python: >=3.12
Provides-Extra: cli
